publicServerAutomator/__init__.py
publicServerAutomator-0.0.1.dist-info/LICENSE
publicServerAutomator-0.0.1.dist-info/METADATA
publicServerAutomator-0.0.1.dist-info/WHEEL
publicServerAutomator-0.0.1.dist-info/top_level.txt
publicServerAutomator-0.0.1.dist-info/RECORD
