Metadata-Version: 2.1
Name: publicServerAutomator
Version: 0.0.1
Summary: An SSH Python automation tool for quickly getting things done
Home-page: https://github.com/gnubyte/publicServerAutomator
Author: Patrick Hastings
Author-email: phastings@openmobo.com
License: UNKNOWN
Platform: UNKNOWN
Classifier: Programming Language :: Python :: 3
Classifier: License :: OSI Approved :: MIT License
Classifier: Operating System :: OS Independent
Requires-Dist: paramiko
